voxel_tool_client/__init__.py
voxel_tool_client-0.2.0.dist-info/METADATA
voxel_tool_client-0.2.0.dist-info/WHEEL
voxel_tool_client-0.2.0.dist-info/top_level.txt
voxel_tool_client-0.2.0.dist-info/RECORD
