Metadata-Version: 2.1
Name: voxel-tool-client
Version: 0.2.0
Summary: voxel_tool_client
Requires-Python: >=3.7
Requires-Dist: requests >=2.31.0
